README
setup.py
Flask_Pyco.egg-info/PKG-INFO
Flask_Pyco.egg-info/SOURCES.txt
Flask_Pyco.egg-info/dependency_links.txt
Flask_Pyco.egg-info/not-zip-safe
Flask_Pyco.egg-info/requires.txt
Flask_Pyco.egg-info/top_level.txt
flask_pyco/__init__.py
flask_pyco/config.py
flask_pyco/page.py
flask_pyco/site.py
flask_pyco/utils.py