Metadata-Version: 1.1
Name: Flask-Pyco
Version: 0.2
Summary: Simple flat file CMS inspired by Pico and Jekyll
Home-page: http://github.com/mosvi/flask-pyco
Author: Miguel Angel Sosvilla Luis
Author-email: msosvi@enlosdetalles.net
License: BSD
Platform: any
Classifier: Environment :: Web Environment
Classifier: Intended Audience :: Developers
Classifier: Framework :: Flask
Classifier: License :: OSI Approved :: BSD License
Classifier: Operating System :: OS Independent
Classifier: Programming Language :: Python
Classifier: Programming Language :: Python :: 3
Classifier: Topic :: Internet :: WWW/HTTP :: Dynamic Content
